<?xml version="1.0" encoding="UTF-8"?>
<Zoo xmlns="http://www.juicers.org"
    xmlns:xsi="http://www.w3.org/2001/XMLSchema-instance"
    xsi:schemaLocation="http://www.juicers.org zoo.xsd">
    <Morada>
        <Pais>Portugal</Pais>
        <Cidade>Porto</Cidade>
        <CodPostal>4440-897</CodPostal>
        <AnoFund>2022</AnoFund>
        <QuantidadeAnimais>10</QuantidadeAnimais>
    </Morada>
    <Animais>
        <Animal>
            <Nome>King Kong</Nome>
            <Descricao>Gorila Africano muito grande mas tranquilo só quer brincadeira da grande e bananas boas para comer, gosta de bater no 
                peito não sei bem porque, deve bater mal da tola ou respira mal dos pulmões</Descricao>
            <SmallDesc>Ola! Eu sou o King Kong , vêm me conhecer melhor!</SmallDesc>
            <Idade>10</Idade>
            <Foto>https://ichef.bbci.co.uk/news/976/cpsprodpb/D2D2/production/_118707935_untitled-1.jpg</Foto>
            <Especie>
                <NomeEspecie>Gorila</NomeEspecie>
                <Tipo>
                    <NomeTipoEspecie>Mamiferos</NomeTipoEspecie>
                    <HabitatTipoEspecie>Mato Grosso</HabitatTipoEspecie>
                    <ImagemTipoEspecie>https://socientifica.com.br/wp-content/uploads/2022/07/mamiferos.jpg</ImagemTipoEspecie>
                    <SmallDescTipoEspecie>Mamíferos são animais que apresentam duas características marcantes: as presenças de pelos no corpo e de glândulas mamárias, as quais produzem leite.</SmallDescTipoEspecie>
                    <DescTipoEspecie>Mamíferos são animais vertebrados, pertencentes à classe Mammalia, que se destacam pela presença de pelos e pela produção de leite. Atualmente existem mais de 5.300 espécies de mamíferos conhecidas, sendo o ser humano uma dessas.</DescTipoEspecie>
                </Tipo>
                <InfoEspecie></InfoEspecie>
                <ImagemEspecie></ImagemEspecie>
                <SubEspecie>
                        <NomeSubEspecie>Africano</NomeSubEspecie>
                        <Local>Africa</Local>
                </SubEspecie>
            </Especie>
        </Animal>
        <Animal>
            <Nome>Simba</Nome>
            <Descricao>Rei da selva gosta da carne temperada com sal e pimenta e rica em proteina para manter o 
                seu shape de rei da selva, gosta também de pentear a juba para ficar todo pomposo para as leoas</Descricao>
            <SmallDesc>Eu sou o rei da selva por isso respect tá</SmallDesc>
            <Idade>7</Idade>
            <Foto>https://www.infoescola.com/wp-content/uploads/2017/04/leao-126767138.jpg</Foto>
            <Especie>
                <NomeEspecie>Leão</NomeEspecie>
                <Tipo>
                    <NomeTipoEspecie>Mamiferos</NomeTipoEspecie>
                    <HabitatTipoEspecie>Mato Grosso</HabitatTipoEspecie>
                    <ImagemTipoEspecie>https://socientifica.com.br/wp-content/uploads/2022/07/mamiferos.jpg</ImagemTipoEspecie>
                    <SmallDescTipoEspecie>Mamíferos são animais que apresentam duas características marcantes: as presenças de pelos no corpo e de glândulas mamárias, as quais produzem leite.</SmallDescTipoEspecie>
                    <DescTipoEspecie>Mamíferos são animais vertebrados, pertencentes à classe Mammalia, que se destacam pela presença de pelos e pela produção de leite. Atualmente existem mais de 5.300 espécies de mamíferos conhecidas, sendo o ser humano uma dessas.</DescTipoEspecie>
                </Tipo>
                <InfoEspecie></InfoEspecie>
                <ImagemEspecie></ImagemEspecie>
                <SubEspecie>
                    <NomeSubEspecie>Africano</NomeSubEspecie>
                    <Local>Selva</Local>
                </SubEspecie>  
            </Especie>
        </Animal>
        <Animal>
            <Nome>Timon</Nome>
            <Descricao>O suricata, também conhecida como suricate ou suricato, é uma espécie de mamífero da família Herpestidae. É a única espécie 
                descrita para o gênero Suricata. Pode ser encontrada na África do Sul,
                 Botsuana, Namíbia e Angola</Descricao>
            <SmallDesc>Soldado do quartel general das suricatas</SmallDesc>
            <Idade>5</Idade>
            <Foto>https://upload.wikimedia.org/wikipedia/commons/thumb/9/96/Meerkat_feb_09.jpg/1200px-Meerkat_feb_09.jpg</Foto>
            <Especie>
                <NomeEspecie>Suricata</NomeEspecie>
                <Tipo>
                    <NomeTipoEspecie>Mamiferos</NomeTipoEspecie>
                    <HabitatTipoEspecie>Mato Grosso</HabitatTipoEspecie>
                    <ImagemTipoEspecie>https://socientifica.com.br/wp-content/uploads/2022/07/mamiferos.jpg</ImagemTipoEspecie>
                    <SmallDescTipoEspecie>Mamíferos são animais que apresentam duas características marcantes: as presenças de pelos no corpo e de glândulas mamárias, as quais produzem leite.</SmallDescTipoEspecie>
                    <DescTipoEspecie>Mamíferos são animais vertebrados, pertencentes à classe Mammalia, que se destacam pela presença de pelos e pela produção de leite. Atualmente existem mais de 5.300 espécies de mamíferos conhecidas, sendo o ser humano uma dessas.</DescTipoEspecie>
                </Tipo>
                <InfoEspecie></InfoEspecie>
                <ImagemEspecie></ImagemEspecie>
                <SubEspecie>
                    <NomeSubEspecie>Africano</NomeSubEspecie>
                    <Local>Floresta</Local>
                </SubEspecie>
            </Especie>
        </Animal>
        <Animal>
            <Nome>Pumba</Nome>
            <Descricao>São mamíferos caracterizados pela cabeça grande, o corpo em forma de barril e a presença de
                 verrugas na cara, o que lhe vale o nome em inglês de warthog ("porco-verruguento") dfsdfsfs</Descricao>
            <SmallDesc>Muito Cabeçudo</SmallDesc>

            <Idade>7</Idade>
            <Foto>https://upload.wikimedia.org/wikipedia/commons/0/01/Tarangire_Warzenschwein1.jpg</Foto>
            <Especie>
                <NomeEspecie>Javali</NomeEspecie>
                <Tipo>
                    <NomeTipoEspecie>Mamiferos</NomeTipoEspecie>
                    <HabitatTipoEspecie>Mato Grosso</HabitatTipoEspecie>
                    <ImagemTipoEspecie>https://socientifica.com.br/wp-content/uploads/2022/07/mamiferos.jpg</ImagemTipoEspecie>
                    <SmallDescTipoEspecie>Mamíferos são animais que apresentam duas características marcantes: as presenças de pelos no corpo e de glândulas mamárias, as quais produzem leite.</SmallDescTipoEspecie>
                    <DescTipoEspecie>Mamíferos são animais vertebrados, pertencentes à classe Mammalia, que se destacam pela presença de pelos e pela produção de leite. Atualmente existem mais de 5.300 espécies de mamíferos conhecidas, sendo o ser humano uma dessas.</DescTipoEspecie>
                </Tipo>
                <InfoEspecie></InfoEspecie>
                <ImagemEspecie></ImagemEspecie>
                <SubEspecie>
                    <NomeSubEspecie>Africano</NomeSubEspecie>
                    <Local>Africa</Local>
                </SubEspecie>
            </Especie>
        </Animal>
        <Animal>
            <Nome>Bambi</Nome>
            <Descricao>O veado-vermelho é um mamífero artiodáctilo ruminante da família Cervidae.
                 É um animal de grande porte, sendo o maior cervídeo depois do alce. Os machos chegam a uma altura no garrote
                 de 1,2 metro e 2,4 metros de comprimento. O peso varia com a região, sendo que mais ao norte os animais
                 tendem a ser maiores: os machos podem pesar até 350 kg na Europa Central, mas na Península Ibérica não 
                 passam dos 250 kg e as fêmeas 150 kg.
                 São mamíferos ungulados pois cada pata se apoia sobre dois dedos que terminam em cascos.</Descricao>
            <SmallDesc>Curnudo</SmallDesc>
            <Idade>10</Idade>
            <Foto>https://www.wilder.pt/wp-content/uploads/2022/06/1280px-Cervus_elaphus_Luc_Viatour_6.jpg</Foto>
            <Especie>
                <NomeEspecie>Veado</NomeEspecie>
                <Tipo>
                    <NomeTipoEspecie>Mamiferos</NomeTipoEspecie>
                    <HabitatTipoEspecie>Mato Grosso</HabitatTipoEspecie>
                    <ImagemTipoEspecie>https://socientifica.com.br/wp-content/uploads/2022/07/mamiferos.jpg</ImagemTipoEspecie>
                    <SmallDescTipoEspecie>Mamíferos são animais que apresentam duas características marcantes: as presenças de pelos no corpo e de glândulas mamárias, as quais produzem leite.</SmallDescTipoEspecie>
                    <DescTipoEspecie>Mamíferos são animais vertebrados, pertencentes à classe Mammalia, que se destacam pela presença de pelos e pela produção de leite. Atualmente existem mais de 5.300 espécies de mamíferos conhecidas, sendo o ser humano uma dessas.</DescTipoEspecie>
                </Tipo>
                <InfoEspecie></InfoEspecie>
                <ImagemEspecie></ImagemEspecie>
                <SubEspecie>
                    <NomeSubEspecie>Vermelho</NomeSubEspecie>
                    <Local>Mar</Local>
                </SubEspecie>
            </Especie>
        </Animal>
        <Animal>
            <Nome>Dumbo</Nome>
            <Descricao>O macho de uma das espécies de Loxodonta, o elefante-da-savana, atinge, em média, 3,2 metros de altura
                 e pesa 6 toneladas, o que o torna o maior animal terrestre existente. 
                O maior espécime já registado tinha cerca de 12.3 toneladas.
                Em comparação com o elefante-asiático do gênero Elephas, distingue-se pelas orelhas maiores (uma adaptação às
                 temperaturas mais elevadas) e pela presença de dentes de marfim nas fêmeas 
                com cerca de 70 quilogramas cada uma.</Descricao>
            <SmallDesc>Obeso com dentes grandes</SmallDesc>
            <Idade>15</Idade>
            <Foto>https://caracolga.pt/wp-content/uploads/2019/01/elefante.jpg</Foto>
            <Especie>
                <NomeEspecie>Elefante</NomeEspecie>
                <Tipo>
                    <NomeTipoEspecie>Mamiferos</NomeTipoEspecie>
                    <HabitatTipoEspecie>Mato Grosso</HabitatTipoEspecie>
                    <ImagemTipoEspecie>https://socientifica.com.br/wp-content/uploads/2022/07/mamiferos.jpg</ImagemTipoEspecie>
                    <SmallDescTipoEspecie>Mamíferos são animais que apresentam duas características marcantes: as presenças de pelos no corpo e de glândulas mamárias, as quais produzem leite.</SmallDescTipoEspecie>
                    <DescTipoEspecie>Mamíferos são animais vertebrados, pertencentes à classe Mammalia, que se destacam pela presença de pelos e pela produção de leite. Atualmente existem mais de 5.300 espécies de mamíferos conhecidas, sendo o ser humano uma dessas.</DescTipoEspecie>
                </Tipo>
                <InfoEspecie></InfoEspecie>
                <ImagemEspecie></ImagemEspecie>
                <SubEspecie>
                    <NomeSubEspecie>Africano</NomeSubEspecie>
                    <Local>Mar</Local>
                </SubEspecie>
            </Especie>
        </Animal>
        <Animal>
            <Nome>Spirit</Nome>
            <Descricao>Os mustangues ou bravios (do inglês: Mustang) são cavalos assilvestrados que ocorrem nos Estados Unidos.
                 São descendentes diretos de cavalos europeus levados para a América por conquistadores espanhóis e portugueses no
                 século XVI. Assim, outros colonizadores, posteriores aos colonizadores ibéricos, encontraram indígenas andando a 
                 cavalo, já que até então não existiam cavalos na América do Sul.São cavalos que mantém seu aspecto físico se
                 alimentando com plantes lenhosas e arbustos Espinhos, sobrevivem a regiões articas e montanhosas,são cavalos rápidos,
                 fortes e resistentes além de serem muito corajosos. Tem uma visão
                 muito boa. Apenas não enxergam bem na parte traseira de seu corpo. Um coice pode chegar a uma tonelada</Descricao>
            <SmallDesc>Cavalo Maluco</SmallDesc>
            <Idade>18</Idade>
            <Foto>https://guiaanimal.net/uploads/content/image/69019/AdobeStock_326500445.jpeg</Foto>
            <Especie>
                <NomeEspecie>Cavalo</NomeEspecie>
                <Tipo>
                    <NomeTipoEspecie>Mamiferos</NomeTipoEspecie>
                    <HabitatTipoEspecie>Mato Grosso</HabitatTipoEspecie>
                    <ImagemTipoEspecie>https://socientifica.com.br/wp-content/uploads/2022/07/mamiferos.jpg</ImagemTipoEspecie>
                    <SmallDescTipoEspecie>Mamíferos são animais que apresentam duas características marcantes: as presenças de pelos no corpo e de glândulas mamárias, as quais produzem leite.</SmallDescTipoEspecie>
                    <DescTipoEspecie>Mamíferos são animais vertebrados, pertencentes à classe Mammalia, que se destacam pela presença de pelos e pela produção de leite. Atualmente existem mais de 5.300 espécies de mamíferos conhecidas, sendo o ser humano uma dessas.</DescTipoEspecie>
                </Tipo>
                <InfoEspecie></InfoEspecie>
                <ImagemEspecie></ImagemEspecie>
                <SubEspecie>
                    <NomeSubEspecie>Mustangue</NomeSubEspecie>
                    <Local>América, Europa</Local>
                </SubEspecie>
            </Especie>
        </Animal>
        <Animal>
            <Nome>Nemo</Nome>
            <Descricao>As espécies assim designadas são nativas de uma vasta região compreendida em águas tépidas do Pacífico,
                 coexistindo algumas espécies em algumas dessas regiões. São famosos devido à relação ecológica de protocooperação
                 que estabelecem com as anémonas-do-mar ou, em alguns casos, com corais. As anémonas providenciam-lhes abrigo, 
                 apesar dos tentáculos urticantes aos quais são imunes, devido à camada de muco que os reveste. O peixe-palhaço
                 esconde-se dos predadores nas anémona. Na base das mesmas, botam seus ovos, assegurando a proteção de sua prole.
                 Em retorno, os restos do alimento
                 do peixe-palhaço são utilizados pela anémona. Uma associação que beneficia os dois parceiros.</Descricao>
            <SmallDesc>Estou perdido</SmallDesc>
            <Idade>5</Idade>
            <Foto>https://www.oceanario.pt/content/img/peixe_palhao_pedro_a._pina.jpg</Foto>
            <Especie>
                <NomeEspecie>Peixe</NomeEspecie>
                <Tipo>
                    <NomeTipoEspecie>Peixes</NomeTipoEspecie>
                    <HabitatTipoEspecie>Mar Grosso</HabitatTipoEspecie>
                    <ImagemTipoEspecie>https://img.freepik.com/vetores-gratis/conjunto-de-peixes-para-ilustracao-de-animais-de-aquario-mar-e-rio_1284-51564.jpg</ImagemTipoEspecie>
                    <SmallDescTipoEspecie>Peixes são animais que vivem em ambiente aquático e apresentam uma série de adaptações a esse ambiente, como a presença de nadadeiras e corpo frequentemente fusiforme.</SmallDescTipoEspecie>
                    <DescTipoEspecie>"Os peixes são animais vertebrados que vivem exclusivamente no ambiente aquático. Possuem diferentes tamanhos, formatos e cores, sendo animais de grande importância econômica, uma vez que são usados na nossa alimentação, em práticas como pesca esportiva e também na criação em aquários, por exemplo. Os peixes possuem um sistema digestório completo, com intestino terminando em cloaca nos peixes cartilaginosos e em ânus nos peixes ósseos. O sistema excretor desses animais é formado por um par de rins. Nos peixes cartilaginosos, é excretado principalmente ureia, e, nos peixes ósseos, observa-se a eliminação de amônia."</DescTipoEspecie>
                </Tipo>
                <InfoEspecie></InfoEspecie>
                <ImagemEspecie></ImagemEspecie>
                <SubEspecie>
                    <NomeSubEspecie>Palhaço</NomeSubEspecie>
                    <Local>Mar</Local>
                </SubEspecie>
            </Especie>
        </Animal>
        <Animal>
            <Nome>Dory</Nome>
            <Descricao>Este pequeno animal tem cerca de 31 centímetros de comprimento e chega a pesar mais de meio quilo. Possui corpo achatado e pele composta
                 principalmente de iridióforos, que são estruturas projetadas para dar brilho aos tons de sua epiderme.
                A cor característica da espécie é um azul profundo, abrangendo a maior parte de seu corpo oval. Possui também algumas
                 linhas com coloração preta, que começam nos olhos, ocupando parte da região superior do peixe, e terminam nas bordas da cauda.
                  Além disso, nesta mesma seção do corpo, possui uma mancha azul, que confere ao peixe sua aparência particular.
                Quanto à cauda, é de cor amarelo fosforescente, que se estende em forma de “V”, com margens escuras. Em sua base,
                 possui um espinho inserido. Além disso, suas barbatanas peitorais têm a mesma cor, apenas em tamanho menor.</Descricao>
            <SmallDesc>Também estou perdido</SmallDesc>
            <Idade>7</Idade>
            <Foto>https://catracalivre.com.br/wp-content/uploads/sites/11/2017/01/IMG_0035.jpg</Foto>
            <Especie>
                <NomeEspecie>cirurgião-patela</NomeEspecie>
                <Tipo>
                    <NomeTipoEspecie>Peixes</NomeTipoEspecie>
                    <HabitatTipoEspecie>Mar Grosso</HabitatTipoEspecie>
                    <ImagemTipoEspecie>https://img.freepik.com/vetores-gratis/conjunto-de-peixes-para-ilustracao-de-animais-de-aquario-mar-e-rio_1284-51564.jpg</ImagemTipoEspecie>
                    <SmallDescTipoEspecie>Peixes são animais que vivem em ambiente aquático e apresentam uma série de adaptações a esse ambiente, como a presença de nadadeiras e corpo frequentemente fusiforme.</SmallDescTipoEspecie>
                    <DescTipoEspecie>"Os peixes são animais vertebrados que vivem exclusivamente no ambiente aquático. Possuem diferentes tamanhos, formatos e cores, sendo animais de grande importância econômica, uma vez que são usados na nossa alimentação, em práticas como pesca esportiva e também na criação em aquários, por exemplo. Os peixes possuem um sistema digestório completo, com intestino terminando em cloaca nos peixes cartilaginosos e em ânus nos peixes ósseos. O sistema excretor desses animais é formado por um par de rins. Nos peixes cartilaginosos, é excretado principalmente ureia, e, nos peixes ósseos, observa-se a eliminação de amônia."</DescTipoEspecie>
                </Tipo>
                <InfoEspecie></InfoEspecie>
                <ImagemEspecie></ImagemEspecie>
                <SubEspecie>
                    <NomeSubEspecie></NomeSubEspecie>
                    <Local>Mar</Local>
                </SubEspecie>
            </Especie>
        </Animal>
        <Animal>
            <Nome>Pô</Nome>
            <Descricao>O panda-gigante é um mamífero de cor preto e branco que come bambu (folhas). A pelagem é grossa e lanosa
                para suportar as baixas temperaturas no ambiente subalpino em que vive. As manchas oculares, membros, orelhas
                e uma faixa que atravessa os ombros são negras; alguma vezes com um tom acastanhado.[28] As restantes partes
                do corpo são brancas, mas podem-se tornar "encardido" com a idade.  A população da região de Qingling apresenta a pelagem em dois tons contrastantes de castanho</Descricao>
            <SmallDesc>Guerreiro dragão</SmallDesc>
            <Idade>15</Idade>
            <Foto>https://bordalo.observador.pt/v2/q:84/rs:fill:2000:1126/c:2000:1126:nowe:0:104/plain/https://s3.observador.pt/wp-content/uploads/2017/01/23132545/76895950.jpg</Foto>
            <Especie>
                <NomeEspecie>Urso</NomeEspecie>
                <Tipo>
                    <NomeTipoEspecie>Mamiferos</NomeTipoEspecie>
                    <HabitatTipoEspecie>Mato Grosso</HabitatTipoEspecie>
                    <ImagemTipoEspecie>https://socientifica.com.br/wp-content/uploads/2022/07/mamiferos.jpg</ImagemTipoEspecie>
                    <SmallDescTipoEspecie>Mamíferos são animais que apresentam duas características marcantes: as presenças de pelos no corpo e de glândulas mamárias, as quais produzem leite.</SmallDescTipoEspecie>
                    <DescTipoEspecie>Mamíferos são animais vertebrados, pertencentes à classe Mammalia, que se destacam pela presença de pelos e pela produção de leite. Atualmente existem mais de 5.300 espécies de mamíferos conhecidas, sendo o ser humano uma dessas.</DescTipoEspecie>
                </Tipo>
                <InfoEspecie></InfoEspecie>
                <ImagemEspecie></ImagemEspecie>
                <SubEspecie>
                    <NomeSubEspecie>Panda</NomeSubEspecie>
                    <Local>Ásia</Local>
                </SubEspecie>
            </Especie>
        </Animal>
        <Animal>
            <Nome>Perry</Nome>
            <Descricao>O ornitorrinco tem corpo hidrodinâmico e comprimido dorsoventralmente. Os membros são curtos e robustos, 
                e os pés possuem membrana interdigital. Cada pé tem cinco dígitos com garras. A cauda é semelhante à de um castor.
                O focinho, que lembra um bico de pato, é alongado e coberto por uma pele glabra, macia, úmida e encouraçada,
                inteiramente perfurado por poros com terminações nervosas sensitivas. As narinas também se abrem no focinho, 
                na metade dorsal superior, e estão posicionadas lado a lado. Os olhos e as orelhas estão localizados em um sulco
                logo após o focinho, esse sulco é fechado por uma pele quando o animal está sob a água. Não tem orelhas externas.
                A ideia de que o ornitorrinco tinha um bico córneo como o das aves surgiu do exame de espécimes ressecados</Descricao>
            <SmallDesc>Sou um pato? um castor? Não! sou um Ornitorrinco</SmallDesc>
            <Idade>18</Idade>
            <Foto>https://imagens.mdig.com.br/bichos/monotremado_ornitorrinco.jpg</Foto>
            <Especie>
                <NomeEspecie>Ornitorrinco</NomeEspecie>
                <Tipo>
                    <NomeTipoEspecie>Mamiferos</NomeTipoEspecie>
                    <HabitatTipoEspecie>Mato Grosso</HabitatTipoEspecie>
                    <ImagemTipoEspecie>https://socientifica.com.br/wp-content/uploads/2022/07/mamiferos.jpg</ImagemTipoEspecie>
                    <SmallDescTipoEspecie>Mamíferos são animais que apresentam duas características marcantes: as presenças de pelos no corpo e de glândulas mamárias, as quais produzem leite.</SmallDescTipoEspecie>
                    <DescTipoEspecie>Mamíferos são animais vertebrados, pertencentes à classe Mammalia, que se destacam pela presença de pelos e pela produção de leite. Atualmente existem mais de 5.300 espécies de mamíferos conhecidas, sendo o ser humano uma dessas.</DescTipoEspecie>
                </Tipo>
                <InfoEspecie></InfoEspecie>
                <ImagemEspecie></ImagemEspecie>
                <SubEspecie>
                    <NomeSubEspecie>Pato</NomeSubEspecie>
                    <Local>Europa</Local>
                </SubEspecie>
            </Especie>
        </Animal>
        <Animal>
            <Nome>Kaa</Nome>
            <Descricao>Anaconda gigante é um termo usado para se referir a uma suposta existência das cobras anacondas com tamanhos maiores do que os normais. A lenda ou crença é baseada em relatos que datam da colonização 
                europeia da América do Sul, quando avistamentos de anacondas gigantes começaram a 
                circular entre os colonos. O tamanho das maiores anacondas tem sido objeto de debate desde então entre criptozoologistas e zoólogos.
                Verificou-se que as anacondas crescem para tamanhos de 5,5 metros e 100 quilos.Em particular, a anaconda verde ou comum é a mais pesada e a maior entre
                 todas as cobras existentes em termos de robustez, e é também a segunda mais longa.
                Enquanto a mais comprida e confirmada anaconda foi de aproximadamente 5,5 m de comprimento, comprimentos muito acima disso foram relatados
                 para esta espécie, sem verificação. Algumas reivindicações descrevem anacondas que variam de 8 a 12 m, embora estas permaneçam não verificadas.</Descricao>
            <SmallDesc>Grande como o caraças come um javali inteirinho </SmallDesc>
            <Idade>10</Idade>
            <Foto>https://i.natgeofe.com/n/f09b5c7c-511b-4ef0-8c70-df2cf86549da/green-anaconda_thumb.jpg</Foto>
            <Especie>
                <NomeEspecie>Anaconda</NomeEspecie>
                <Tipo>
                    <NomeTipoEspecie>Repteis</NomeTipoEspecie>
                    <HabitatTipoEspecie>Mato Grosso</HabitatTipoEspecie>
                    <ImagemTipoEspecie>https://img.freepik.com/vetores-premium/repteis-e-anfibios-sapo-dos-desenhos-animados-camaleao-crocodilo-lagarto-e-tartaruga-conjunto-de-ilustracao-vetorial-de-animais-selvagens-serpente-reptil-e-anfibios_229548-1855.jpg</ImagemTipoEspecie>
                    <SmallDescTipoEspecie>Réptil é um termo utilizado para referir-se a animais com pele grossa, com respiração pulmonar e que, geralmente, põem ovos,</SmallDescTipoEspecie>
                    <DescTipoEspecie>Os répteis são animais amniotas, tetrápodes e ectotérmicos. Damos o nome de amniotas aos animais que apresentam embriões envolvidos pela membrana amniótica, de tetrápodes aos animais que apresentam quatro membros, e de ectotérmicos àqueles que não são capazes de manter a temperatura do corpo constante utilizando-se de seu metabolismo.O fato dos répteis serem animais ectotérmicos é o motivo pelo qual são chamados de animais de “sangue frio” e de não serem capazes de viver em regiões muito frias, como os polos. Para aquecerem seu corpo, os répteis precisam expor-se ao Sol, e para resfriarem-no, precisam esconder-se dele.</DescTipoEspecie>
                </Tipo>
                <InfoEspecie></InfoEspecie>
                <ImagemEspecie></ImagemEspecie>
                <SubEspecie>
                    <NomeSubEspecie>Gigante</NomeSubEspecie>
                    <Local>Brasil</Local>
                </SubEspecie>
            </Especie>
        </Animal>
        <Animal>
            <Nome>Oogway</Nome>
            <Descricao>As tartarugas-gigante que existem hoje em dia são características de habitats insulares da região tropical.
                 O registo fóssil, no entanto, mostra que já foram comuns nos continentes, em particular na Ásia. 
                 As tartarugas-gigante têm dimensões variáveis, de espécie para espécie. As maiores atingem 300 kg de peso e 1.3 metros de comprimento.
                 A maior população de tartarugas-gigante encontra-se no atol de Aldabra, no oceano Índico, com cerca de 100.000 exemplares de tartaruga-gigante-de-aldabra
                  (Geochelone gigantea).</Descricao>
            <SmallDesc>Muita sabedoria para escolher o guerreiro dragão </SmallDesc>
            <Idade>20</Idade>
            <Foto>https://www.pensamentoverde.com.br/wp-content/uploads/2018/02/tartaruga-gigante.jpg</Foto>
            <Especie>
                <NomeEspecie>Tartaruga</NomeEspecie>
                <Tipo>
                    <NomeTipoEspecie>Repteis</NomeTipoEspecie>
                    <HabitatTipoEspecie>Mato Grosso</HabitatTipoEspecie>
                    <ImagemTipoEspecie>https://img.freepik.com/vetores-premium/repteis-e-anfibios-sapo-dos-desenhos-animados-camaleao-crocodilo-lagarto-e-tartaruga-conjunto-de-ilustracao-vetorial-de-animais-selvagens-serpente-reptil-e-anfibios_229548-1855.jpg</ImagemTipoEspecie>
                    <SmallDescTipoEspecie>Réptil é um termo utilizado para referir-se a animais com pele grossa, com respiração pulmonar e que, geralmente, põem ovos,</SmallDescTipoEspecie>
                    <DescTipoEspecie>Os répteis são animais amniotas, tetrápodes e ectotérmicos. Damos o nome de amniotas aos animais que apresentam embriões envolvidos pela membrana amniótica, de tetrápodes aos animais que apresentam quatro membros, e de ectotérmicos àqueles que não são capazes de manter a temperatura do corpo constante utilizando-se de seu metabolismo.O fato dos répteis serem animais ectotérmicos é o motivo pelo qual são chamados de animais de “sangue frio” e de não serem capazes de viver em regiões muito frias, como os polos. Para aquecerem seu corpo, os répteis precisam expor-se ao Sol, e para resfriarem-no, precisam esconder-se dele.</DescTipoEspecie>
                </Tipo>
                <InfoEspecie></InfoEspecie>
                <ImagemEspecie></ImagemEspecie>
                <SubEspecie>
                    <NomeSubEspecie>Gigante</NomeSubEspecie>
                    <Local>Brasil</Local>
                </SubEspecie>
            </Especie>
        </Animal>
        <Animal>
            <Nome>Blue</Nome>
            <Descricao>A arara-azul, também conhecida como arara-azul-grande, pertence à espécie Anodorhynchus hyacinthinus. Possui coloração predominantemente azul-cobalto,
                 com regiões em amarelo ao redor dos olhos e na mandíbula inferior. Apresenta a pele em volta da mandíbula na forma de fita.
                 Essa é uma ave de grande porte com cerca de 1,0 m de comprimento da cabeça à cauda e 1,20 m de envergadura, pesando, aproximadamente, 1,3 kg.</Descricao>
            <SmallDesc>Tenho asas mas não sei voar</SmallDesc>
            <Idade>6</Idade>
            <Foto>https://websitly.com/sites/default/files/produtos/foto-projeto-arara-azul.jpg</Foto>
            <Especie>
                <NomeEspecie>Arara</NomeEspecie>
                <Tipo>
                    <NomeTipoEspecie>Aves</NomeTipoEspecie>
                    <HabitatTipoEspecie>Ar Grosso</HabitatTipoEspecie>
                    <ImagemTipoEspecie>https://img.freepik.com/vetores-gratis/diferentes-tipos-de-colecao-de-passaros_1308-98105.jpg?w=2000</ImagemTipoEspecie>
                    <SmallDescTipoEspecie>As aves são animais vertebrados que se destacam pela presença de suas penas, uma característica exclusiva deste grupo</SmallDescTipoEspecie>
                    <DescTipoEspecie>As aves são animais vertebrados que apresentam como característica mais marcante a presença de penas, as quais são feitas de queratina, mesma proteína encontrada na escama dos répteis. Outra característica marcante é o fato de esses animais serem endotérmicos, ou seja, mantêm a temperatura constante do seu corpo graças ao seu metabolismo. Com isso, esses animais podem viver em diferentes ambientes, uma vez que não precisam do calor externo para se aquecer. Encontramos aves em quase todos os lugares do planeta, sendo possível observá-las, por exemplo, em regiões desérticas, nos polos, nas florestas e ilhas oceânicas.</DescTipoEspecie>
                </Tipo>
                <InfoEspecie></InfoEspecie>
                <ImagemEspecie></ImagemEspecie>
                <SubEspecie>
                    <NomeSubEspecie>azul-gigante</NomeSubEspecie>
                    <Local>Brasil</Local>
                </SubEspecie>
            </Especie>
        </Animal>
        <Animal>
            <Nome>Zazu</Nome>
            <Descricao>Este calau tem entre 42 a 50 cm de comprimento, sendo os machos um pouco maiores que as fêmeas. A sua plumagem tem um padrão complexo de branco e negro: 
                face, pescoço, garganta e zona ventral são brancas, enquanto que o dorso,
                cauda, crista e parte posterior do pescoço são pretos. As asas são sobretudo negras, com manchas brancas. A sua característica mais típica é o bico longo,
                ligeiramente encurvado e vermelho vivo.

                O calau-de-bico-vermelho tem uma alimentação à base de insectos e outros invertebrados, 
                suplementada com sementes e ovos de pequenas aves, principalmente tecelões. É uma ave gregária, que vive em pequenos bandos,
                 excepto na época de reprodução, quando forma casais. O seu vôo é ondulante.</Descricao>
            <SmallDesc>Tenho asas mas não sei voar</SmallDesc>
            <Idade>6</Idade>
            <Foto>https://live.staticflickr.com/4058/4363245253_da441abfa9_b.jpg</Foto>
            <Especie>
                <NomeEspecie>calau-de-bico-vermelho</NomeEspecie>
                <Tipo>
                    <NomeTipoEspecie>Aves</NomeTipoEspecie>
                    <HabitatTipoEspecie>Ar Grosso</HabitatTipoEspecie>
                    <ImagemTipoEspecie>https://img.freepik.com/vetores-gratis/diferentes-tipos-de-colecao-de-passaros_1308-98105.jpg?w=2000</ImagemTipoEspecie>
                    <SmallDescTipoEspecie>As aves são animais vertebrados que se destacam pela presença de suas penas, uma característica exclusiva deste grupo</SmallDescTipoEspecie>
                    <DescTipoEspecie>As aves são animais vertebrados que apresentam como característica mais marcante a presença de penas, as quais são feitas de queratina, mesma proteína encontrada na escama dos répteis. Outra característica marcante é o fato de esses animais serem endotérmicos, ou seja, mantêm a temperatura constante do seu corpo graças ao seu metabolismo. Com isso, esses animais podem viver em diferentes ambientes, uma vez que não precisam do calor externo para se aquecer. Encontramos aves em quase todos os lugares do planeta, sendo possível observá-las, por exemplo, em regiões desérticas, nos polos, nas florestas e ilhas oceânicas.</DescTipoEspecie>
                </Tipo>
                <InfoEspecie></InfoEspecie>
                <ImagemEspecie></ImagemEspecie>
                <SubEspecie>
                    <NomeSubEspecie></NomeSubEspecie>
                    <Local>Africa</Local>
                </SubEspecie>
            </Especie>
        </Animal>
    </Animais>
    <Funcionarios>
        <funcionario>
            <Nome>Henrique</Nome>
            <Descricao>Jogar ás escondidas</Descricao>
            <Especialidade>Felinos</Especialidade>
        </funcionario>
        <funcionario>
            <Nome>Alexandre</Nome>
            <Descricao>Jogar airsoft ou lá o que é</Descricao>
            <Especialidade>Caçador</Especialidade>
        </funcionario>
        <funcionario>
            <Nome>Garrido</Nome>
            <Descricao>Estagiário</Descricao>
            <Especialidade>Ainda por apurar</Especialidade>
        </funcionario>
    </Funcionarios>
    <Loja>
        <Artigo>
            <Nome>Pluxe Leão</Nome>
            <Preco>20.00</Preco>
            <Categoria>Artigo</Categoria>
            <Quantidade>30</Quantidade>
        </Artigo>
        <Artigo>
            <Nome>Pluxe Nemo</Nome>
            <Preco>20.00</Preco>
            <Categoria>Artigo</Categoria>
            <Quantidade>20</Quantidade>
        </Artigo>
        <Artigo>
            <Nome>Pluxe Tigre</Nome>
            <Preco>20.00</Preco>
            <Categoria>Artigo</Categoria>
            <Quantidade>50</Quantidade>
        </Artigo>
        <Artigo>
            <Nome>Bilhete Adulto</Nome>
            <Preco>29.99</Preco>
            <Categoria>Bilhete</Categoria>
            <Quantidade>100</Quantidade>
        </Artigo>
        <Artigo>
            <Nome>Bilhete Idoso</Nome>
            <Preco>19.99</Preco>
            <Categoria>Bilhete</Categoria>
            <Quantidade>100</Quantidade>
        </Artigo>
        <Artigo>
            <Nome>Bilhete Criança</Nome>
            <Preco>9.99</Preco>
            <Categoria>Bilhete</Categoria>
            <Quantidade>100</Quantidade>
        </Artigo>
    </Loja>
</Zoo>